__init__.py
kintsugi/__init__.py
kintsugi/api.py
kintsugi/model.py
kintsugi/parsers.py
kintsugi_python-0.1.8.dist-info/LICENSE
kintsugi_python-0.1.8.dist-info/METADATA
kintsugi_python-0.1.8.dist-info/WHEEL
kintsugi_python-0.1.8.dist-info/top_level.txt
kintsugi_python-0.1.8.dist-info/RECORD
