Metadata-Version: 2.1
Name: kintsugi-python
Version: 0.1.8
Summary: Python SDK to access Kintsugi Voice API V2.
Author-email: Kintsugi Engineering Team <python-sdk@kintsugihealth.com>
License: MIT
Requires-Python: >=3.8.0
License-File: LICENSE
Requires-Dist: requests >=2.31.0
Requires-Dist: pytest >=8.2.0
